ogdp_apis/__init__.py
ogdp_apis/aqi/__init__.py
ogdp_apis/aqi/aqi.py
ogdp_apis-0.1.dist-info/METADATA
ogdp_apis-0.1.dist-info/WHEEL
ogdp_apis-0.1.dist-info/top_level.txt
ogdp_apis-0.1.dist-info/RECORD
