Metadata-Version: 2.1
Name: ogdp-apis
Version: 0.1
Summary: A python wrapper for data.gov.in APIs
Home-page: https://github.com/masala-man/ogdp-apis
Author: Ayush Shenoy
Author-email: masala_man@protonmail.com
License: UNKNOWN
Platform: UNKNOWN
Classifier: Programming Language :: Python :: 3
Classifier: License :: OSI Approved :: MIT License
Classifier: Operating System :: OS Independent
Requires-Python: >=3.6
